mmpm/__init__.py
mmpm/__version__.py
mmpm/entrypoint.py
mmpm/env.py
mmpm/singleton.py
mmpm/ui.py
mmpm/utils.py
mmpm/wsgi.py
mmpm/api/__init__.py
mmpm/api/entrypoint.py
mmpm/api/repeater.py
mmpm/api/constants/http.py
mmpm/api/endpoints/__init__.py
mmpm/api/endpoints/endpoint.py
mmpm/api/endpoints/ep_configs.py
mmpm/api/endpoints/ep_db.py
mmpm/api/endpoints/ep_env.py
mmpm/api/endpoints/ep_logs.py
mmpm/api/endpoints/ep_mm_ctl.py
mmpm/api/endpoints/ep_mmpm.py
mmpm/api/endpoints/ep_packages.py
mmpm/api/endpoints/index.py
mmpm/constants/__init__.py
mmpm/constants/color.py
mmpm/constants/paths.py
mmpm/constants/urls.py
mmpm/log/__init__.py
mmpm/log/factory.py
mmpm/log/server.py
mmpm/magicmirror/__init__.py
mmpm/magicmirror/controller.py
mmpm/magicmirror/database.py
mmpm/magicmirror/magicmirror.py
mmpm/magicmirror/package.py
mmpm/subcommands/__init__.py
mmpm/subcommands/_sub_cmd_completion.py
mmpm/subcommands/_sub_cmd_db.py
mmpm/subcommands/_sub_cmd_env.py
mmpm/subcommands/_sub_cmd_guided_setup.py
mmpm/subcommands/_sub_cmd_install.py
mmpm/subcommands/_sub_cmd_list.py
mmpm/subcommands/_sub_cmd_logs.py
mmpm/subcommands/_sub_cmd_mm_ctl.py
mmpm/subcommands/_sub_cmd_mm_pkg.py
mmpm/subcommands/_sub_cmd_open.py
mmpm/subcommands/_sub_cmd_remove.py
mmpm/subcommands/_sub_cmd_search.py
mmpm/subcommands/_sub_cmd_show.py
mmpm/subcommands/_sub_cmd_ui.py
mmpm/subcommands/_sub_cmd_update.py
mmpm/subcommands/_sub_cmd_upgrade.py
mmpm/subcommands/_sub_cmd_version.py
mmpm/subcommands/loader.py
mmpm/subcommands/sub_cmd.py
mmpm/ui/app.component.css.map
mmpm/ui/custom-package-manager.component.css.map
mmpm/ui/database-info.component.css.map
mmpm/ui/favicon.ico
mmpm/ui/index.html
mmpm/ui/log-stream-viewer.component.css.map
mmpm/ui/main.js
mmpm/ui/main.js.map
mmpm/ui/marketplace.component.css.map
mmpm/ui/package-details-viewer.component.css.map
mmpm/ui/polyfills.js
mmpm/ui/polyfills.js.map
mmpm/ui/shopping-cart.component.css.map
mmpm/ui/styles.css
mmpm/ui/styles.css.map
mmpm-4.3.0.dist-info/METADATA
mmpm-4.3.0.dist-info/WHEEL
mmpm-4.3.0.dist-info/entry_points.txt
mmpm-4.3.0.dist-info/licenses/LICENSE.md
mmpm-4.3.0.dist-info/RECORD
