Metadata-Version: 2.4
Name: mmpm
Version: 4.3.0
Summary: MMPM, the MagicMirror Package Manager CLI simplifies the installation, removal, and general maintenance of MagicMirror packages
Project-URL: Homepage, https://github.com/Bee-Mar/mmpm
Project-URL: Downloads, https://github.com/Bee-Mar/mmpm/archive/4.2.6.tar.gz
Author-email: Brandon Marlowe <bpmarlowe-software@protonmail.com>
License: MIT
License-File: LICENSE.md
Keywords: MagicMirror magicmirror package-manager mmpm MMPM magicmirror-package-manager package manager magicmirror_package_manager
Requires-Python: >=3.10
Requires-Dist: argcomplete<4.0.0,>=3.5.3
Requires-Dist: argparse<2.0.0,>=1.4.0
Requires-Dist: colorama<1.0.0,>=0.4.6
Requires-Dist: flask-cors<6.0.0,>=5.0.0
Requires-Dist: flask-socketio<6.0.0,>=5.5.1
Requires-Dist: flask<4.0.0,>=3.1.0
Requires-Dist: gevent-websocket<1.0.0,>=0.10.1
Requires-Dist: gevent<25.0.0,>=24.11.1
Requires-Dist: gitpython<4.0.0,>=3.1.44
Requires-Dist: gunicorn<24.0.0,>=23.0.0
Requires-Dist: importlib-resources<7.0.0,>=6.5.2
Requires-Dist: jinja2<4.0.0,>=3.1.5
Requires-Dist: prompt-toolkit<4.0.0,>=3.0.48
Requires-Dist: pygments<3.0.0,>=2.19.1
Requires-Dist: python-socketio[client]<6.0.0,>=5.12.1
Requires-Dist: requests<3.0.0,>=2.32.3
Requires-Dist: yaspin<4.0.0,>=3.1.0
